tests/__init__.py
tests/helper.py
tests/test_acme_v02.py
tests/test_crypto.py
triplecask/__init__.py
triplecask/crypto.py
triplecask/acme_v02/__init__.py
triplecask/acme_v02/acme.py
triplecask/acme_v02/types.py
triplecask-0.6.0.dist-info/DESCRIPTION.rst
triplecask-0.6.0.dist-info/METADATA
triplecask-0.6.0.dist-info/RECORD
triplecask-0.6.0.dist-info/WHEEL
triplecask-0.6.0.dist-info/metadata.json
triplecask-0.6.0.dist-info/top_level.txt
