Metadata-Version: 2.0
Name: triplecask
Version: 0.6.0
Summary: UNKNOWN
Home-page: UNKNOWN
Author: Mihir Singh (@citruspi)
Author-email: pypi.service@mihirsingh.com
License: UNKNOWN
Platform: any
Requires-Python: >=3.6
Provides-Extra: dev
Provides-Extra: pyopenssl
Provides-Extra: dev
Requires-Dist: nose; extra == 'dev'
Requires-Dist: coverage; extra == 'dev'
Provides-Extra: pyopenssl
Requires-Dist: pyopenssl; extra == 'pyopenssl'
